pyifpni/__init__.py
pyifpni/pyifpni.py
pyIFPNI-0.2.1.dist-info/LICENSE
pyIFPNI-0.2.1.dist-info/METADATA
pyIFPNI-0.2.1.dist-info/WHEEL
pyIFPNI-0.2.1.dist-info/top_level.txt
pyIFPNI-0.2.1.dist-info/RECORD
