Metadata-Version: 2.1
Name: pyIFPNI
Version: 0.2.1
Summary: A package accessing to IFPNI
Home-page: https://github.com/WDragon101/pyIFPNI
Author: Bailong Zhao
Author-email: bailongzhao@163.com
Classifier: Programming Language :: Python :: 3
Classifier: License :: OSI Approved :: MIT License
Classifier: Operating System :: OS Independent
License-File: LICENSE
